MANIFEST.in
README.md
requirements-inst.txt
requirements-test.txt
requirements.txt
setup.py
jaegermeister/__init__.py
jaegermeister/constants.py
jaegermeister/instrumentation.py
jaegermeister/utils.py
jaegermeister.egg-info/PKG-INFO
jaegermeister.egg-info/SOURCES.txt
jaegermeister.egg-info/dependency_links.txt
jaegermeister.egg-info/entry_points.txt
jaegermeister.egg-info/requires.txt
jaegermeister.egg-info/top_level.txt
jaegermeister/libraries/__init__.py
jaegermeister/libraries/django_/__init__.py
jaegermeister/libraries/django_/apps.py
jaegermeister/libraries/django_/instrument.py
jaegermeister/libraries/elasticsearch_/__init__.py
jaegermeister/libraries/elasticsearch_/instrument.py
jaegermeister/libraries/flask_/__init__.py
jaegermeister/libraries/flask_/instrument.py
jaegermeister/libraries/psycopg2_/__init__.py
jaegermeister/libraries/psycopg2_/instrument.py
jaegermeister/libraries/pymongo_/__init__.py
jaegermeister/libraries/pymongo_/instrument.py
jaegermeister/libraries/pymysql_/__init__.py
jaegermeister/libraries/pymysql_/instrument.py
jaegermeister/libraries/redis_/__init__.py
jaegermeister/libraries/redis_/instrument.py
jaegermeister/libraries/requests_/__init__.py
jaegermeister/libraries/requests_/instrument.py
jaegermeister/libraries/tornado_/__init__.py
jaegermeister/libraries/tornado_/instrument.py
scripts/__init__.py
scripts/bootstrap.py
scripts/sfx_py_trace.py
scripts/site_/__init__.py
scripts/site_/sitecustomize.py