Metadata-Version: 2.1
Name: jaegermeister
Version: 0.0.604
Summary: Provides auto-instrumentation for OpenTracing-traced libraries and frameworks
Home-page: UNKNOWN
Author: Sagi @ L
License: Apache Software License v2
Platform: UNKNOWN
Classifier: Development Status :: 4 - Beta
Classifier: Intended Audience :: Developers
Classifier: Natural Language :: English
Classifier: License :: OSI Approved :: Apache Software License
Classifier: Programming Language :: Python
Classifier: Programming Language :: Python :: 2
Classifier: Programming Language :: Python :: 2.7
Classifier: Programming Language :: Python :: 3
Classifier: Programming Language :: Python :: 3.4
Classifier: Programming Language :: Python :: 3.5
Classifier: Programming Language :: Python :: 3.6
Provides-Extra: pymongo
Provides-Extra: all
Provides-Extra: elasticsearch
Provides-Extra: pymysql
Provides-Extra: flask
Provides-Extra: django
Provides-Extra: psycopg2
Provides-Extra: redis
Provides-Extra: unit_tests
Provides-Extra: instrumentation_tests
Provides-Extra: tornado
Provides-Extra: dbapi
Provides-Extra: jaeger
Provides-Extra: requests
